Spoiled/__init__.py
Spoiled/Database/__init__.py
Spoiled/Database/chat_words.py
Spoiled/Database/chats.py
Spoiled/Database/coins.py
Spoiled/Database/completed.py
Spoiled/Database/global_stats.py
Spoiled/Database/privacy.py
Spoiled/Database/record.py
Spoiled/Database/user_chat_info.py
Spoiled/Database/users.py
Spoiled/Shannu/__init__.py
Spoiled/Shannu/alpha.py
Spoiled/Shannu/config.py
Spoiled/Shannu/shivi.py
Spoiled/Shannu/words.py
Spoiled/SpoiledPlugins/__init__.py
Spoiled/SpoiledPlugins/callbacks.py
Spoiled/SpoiledPlugins/coins.py
Spoiled/SpoiledPlugins/eval.py
Spoiled/SpoiledPlugins/fw.py
Spoiled/SpoiledPlugins/handlers.py
Spoiled/SpoiledPlugins/help.py
Spoiled/SpoiledPlugins/image.py
Spoiled/SpoiledPlugins/inline.py
Spoiled/SpoiledPlugins/leaderboard.py
Spoiled/SpoiledPlugins/served.py
Spoiled/SpoiledPlugins/start.py
Spoiled/SpoiledPlugins/templates.py
Spoiled/SpoiledPlugins/watchers.py
SpLFastlyWrite-1.0.9.dist-info/LICENSE
SpLFastlyWrite-1.0.9.dist-info/METADATA
SpLFastlyWrite-1.0.9.dist-info/WHEEL
SpLFastlyWrite-1.0.9.dist-info/top_level.txt
SpLFastlyWrite-1.0.9.dist-info/RECORD
