Metadata-Version: 2.1
Name: SpLFastlyWrite
Version: 1.0.9
Summary: SpLFastlyWrite
Home-page: https://github.com/ShutupKeshav/SpLFastlyWrite
Download-URL: https://github.com/ShutupKeshav/SpLFastlyWrite/releases/latest
Author: ShutupKeshav
Author-email: keshavatripathi@yahoo.com
License: MIT
Project-URL: Tracker, https://github.com/ShutupKeshav/SpLFastlyWrite/issues
Project-URL: Community, https://t.me/SpLBots
Project-URL: Source, https://github.com/ShutupKeshav/SpLFastlyWrite
Project-URL: Documentation, https://t.me/SpLBots
Keywords: SpLFastlyWrite
Requires-Python: ~=3.7
License-File: LICENSE
